{
  "name": "AA-Common-Numbers",
  "entries": [
    { "from": "\u0152", "to": "०", "order": 20, "comment": "0" },
    { "from": "\u0192", "to": "१", "order": 20, "comment": "1" },
    { "from": "\u201E", "to": "२", "order": 20, "comment": "2" },
    { "from": "\u2026", "to": "३", "order": 20, "comment": "3" },
    { "from": "\u2020", "to": "४", "order": 20, "comment": "4" },
    { "from": "\u2021", "to": "५", "order": 20, "comment": "5" },
    { "from": "\u02C6", "to": "६", "order": 20, "comment": "6" },
    { "from": "\u2030", "to": "७", "order": 20, "comment": "7" },
    { "from": "\u0160", "to": "८", "order": 20, "comment": "8" },
    { "from": "\u2039", "to": "९", "order": 20, "comment": "9" }
  ]
}